{
  "date": "2025-10-17",
  "period": {
    "start": "2025-10-16T06:00:00+08:00",
    "end": "2025-10-17T06:00:00+08:00"
  },
  "aircraft": {
    "total": 18,
    "crossed_median": 18,
    "entered_adiz": 18,
    "adiz_regions": [
      "north",
      "southwest",
      "southeast"
    ]
  },
  "vessels": {
    "naval": 9,
    "official": 0
  },
  "map_image": "assets/maps/2025-10-17.jpg",
  "positions": {
    "source": "zones",
    "aircraft": [
      {
        "lat": 25.5,
        "lon": 121.0,
        "label": "north"
      },
      {
        "lat": 22.5,
        "lon": 119.5,
        "label": "southwest"
      },
      {
        "lat": 22.5,
        "lon": 121.5,
        "label": "southeast"
      }
    ],
    "vessels": [
      {
        "lat": 24.5,
        "lon": 120.5,
        "type": "naval"
      }
    ]
  },
  "source_url": "https://www.mnd.gov.tw/news/plaact/85017"
}